odoo/addons/sale_purchase_force_vendor/README.rst
odoo/addons/sale_purchase_force_vendor/__init__.py
odoo/addons/sale_purchase_force_vendor/__manifest__.py
odoo/addons/sale_purchase_force_vendor/i18n/es.po
odoo/addons/sale_purchase_force_vendor/i18n/sale_purchase_force_vendor.pot
odoo/addons/sale_purchase_force_vendor/models/__init__.py
odoo/addons/sale_purchase_force_vendor/models/res_company.py
odoo/addons/sale_purchase_force_vendor/models/res_config_settings.py
odoo/addons/sale_purchase_force_vendor/models/sale_order_line.py
odoo/addons/sale_purchase_force_vendor/models/stock_move.py
odoo/addons/sale_purchase_force_vendor/readme/CONFIGURE.rst
odoo/addons/sale_purchase_force_vendor/readme/CONTRIBUTORS.rst
odoo/addons/sale_purchase_force_vendor/readme/DESCRIPTION.rst
odoo/addons/sale_purchase_force_vendor/readme/USAGE.rst
odoo/addons/sale_purchase_force_vendor/static/description/icon.png
odoo/addons/sale_purchase_force_vendor/static/description/index.html
odoo/addons/sale_purchase_force_vendor/tests/__init__.py
odoo/addons/sale_purchase_force_vendor/tests/common.py
odoo/addons/sale_purchase_force_vendor/tests/test_sale_purchase_force_vendor.py
odoo/addons/sale_purchase_force_vendor/views/res_config_settings_view.xml
odoo/addons/sale_purchase_force_vendor/views/sale_order_view.xml
odoo14_addon_sale_purchase_force_vendor-14.0.2.0.0.dist-info/METADATA
odoo14_addon_sale_purchase_force_vendor-14.0.2.0.0.dist-info/WHEEL
odoo14_addon_sale_purchase_force_vendor-14.0.2.0.0.dist-info/top_level.txt
odoo14_addon_sale_purchase_force_vendor-14.0.2.0.0.dist-info/RECORD
