Metadata-Version: 2.1
Name: odoo14-addon-sale-purchase-force-vendor
Version: 14.0.2.0.0
Summary: Sale Purchase Force Vendor
Home-page: https://github.com/OCA/purchase-workflow
Author: Tecnativa, Odoo Community Association (OCA)
Author-email: support@odoo-community.org
License: AGPL-3
Platform: UNKNOWN
Classifier: Programming Language :: Python
Classifier: Framework :: Odoo
Classifier: Framework :: Odoo :: 14.0
Classifier: License :: OSI Approved :: GNU Affero General Public License v3
Requires-Python: >=3.6
Requires-Dist: odoo14-addon-web-domain-field
Requires-Dist: odoo (<14.1dev,>=14.0a)
